ppnet/__init__.py
ppnet/create_net.py
ppnet/create_phylogenetic_profile.py
ppnet/genome_qc.py
ppnet/network_plot.py
ppnet/ppnet.py
ppnet/method/__init__.py
ppnet/method/methods.py
ppnet-1.0.2.dist-info/LICENSE
ppnet-1.0.2.dist-info/METADATA
ppnet-1.0.2.dist-info/WHEEL
ppnet-1.0.2.dist-info/top_level.txt
ppnet-1.0.2.dist-info/RECORD
