Metadata-Version: 2.1
Name: ppnet
Version: 1.0.2
Summary: A package for identifying functional association networks by phylogenetic profiling of prokaryotic genomes.
Home-page: https://github.com/liyangjie/PPNet
Author: liyangjie
Author-email: 335659173@qq.com
License: GNU General Public License v3.0
Keywords: Functional association network inference,Phylogenetic profiling,Prokaryotic genome,de-replication
Classifier: License :: OSI Approved :: GNU General Public License v3 (GPLv3)
Classifier: Topic :: Scientific/Engineering :: Bio-Informatics
Classifier: Programming Language :: Python :: 3.7
Classifier: Programming Language :: Python :: 3.8
Classifier: Programming Language :: Python :: 3.9
License-File: LICENSE
Requires-Dist: biopython
Requires-Dist: pyvis
Requires-Dist: numpy
Requires-Dist: scipy
Requires-Dist: statsmodels
Requires-Dist: kneed
Requires-Dist: pyani
